colorama-stubs/METADATA.toml
colorama-stubs/__init__.pyi
colorama-stubs/ansi.pyi
colorama-stubs/ansitowin32.pyi
colorama-stubs/initialise.pyi
colorama-stubs/win32.pyi
colorama-stubs/winterm.pyi
types_colorama-0.4.15.20240310.dist-info/METADATA
types_colorama-0.4.15.20240310.dist-info/WHEEL
types_colorama-0.4.15.20240310.dist-info/top_level.txt
types_colorama-0.4.15.20240310.dist-info/RECORD
